mctspy/__init__.py
mctspy/games/__init__.py
mctspy/games/common.py
mctspy/games/examples/__init__.py
mctspy/games/examples/tictactoe.py
mctspy/tree/__init__.py
mctspy/tree/nodes.py
mctspy/tree/search.py
mctspy-0.1.1.dist-info/LICENSE
mctspy-0.1.1.dist-info/METADATA
mctspy-0.1.1.dist-info/WHEEL
mctspy-0.1.1.dist-info/top_level.txt
mctspy-0.1.1.dist-info/RECORD
