Metadata-Version: 2.1
Name: mctspy
Version: 0.1.1
Summary: Python implementation of monte carlo tree search for 2 players zero-sum game 
Home-page: https://github.com/int8/monte-carlo-tree-search
Author: Kamil Czarnogórski
License: UNKNOWN
Keywords: mcts monte carlo tree search
Platform: UNKNOWN
Classifier: Programming Language :: Python :: 3
Classifier: Programming Language :: Python :: 3.5
Classifier: Programming Language :: Python :: 3.6
Classifier: Programming Language :: Python :: 3.7
Classifier: License :: OSI Approved :: MIT License
Classifier: Operating System :: OS Independent
Requires-Python: >=3.5.7
